mlflow_log_cli/__init__.py
mlflow_log_cli/cli.py
mlflow_log_cli/json_file.py
mlflow_log_cli-0.1.0.dist-info/entry_points.txt
mlflow_log_cli-0.1.0.dist-info/LICENSE
mlflow_log_cli-0.1.0.dist-info/WHEEL
mlflow_log_cli-0.1.0.dist-info/METADATA
mlflow_log_cli-0.1.0.dist-info/RECORD
