Metadata-Version: 2.1
Name: mlflow-log-cli
Version: 0.1.0
Summary: 
Author: なるみ
Author-email: weaper@gmail.com
Requires-Python: >=3.8,<3.9
Classifier: Programming Language :: Python :: 3
Classifier: Programming Language :: Python :: 3.8
Requires-Dist: click (>=8.1.3,<9.0.0)
Requires-Dist: loguru (>=0.6.0,<0.7.0)
Requires-Dist: mlflow (>=1.26.1,<2.0.0)
